multiptesttry/__init__.py
multiptesttry/multiple.py
multiptesttry-0.0.2.dist-info/METADATA
multiptesttry-0.0.2.dist-info/WHEEL
multiptesttry-0.0.2.dist-info/top_level.txt
multiptesttry-0.0.2.dist-info/RECORD
