Metadata-Version: 2.1
Name: multiptesttry
Version: 0.0.2
Summary: Array simple product
Author: Aimane
Author-email: <aelmaimouni@leyton.com>
License: UNKNOWN
Keywords: python,product,tensors,arrays
Platform: UNKNOWN
Classifier: Development Status :: 1 - Planning
Classifier: Intended Audience :: Developers
Classifier: Programming Language :: Python :: 3
Classifier: Operating System :: Microsoft :: Windows
Requires-Dist: numpy
